fast_tracker/FastTracker.json
fast_tracker/__init__.py
fast_tracker/config.py
fast_tracker/decorators.py
fast_tracker/fast_tracker.py
fast_tracker/fast_tracker_configer.py
fast_tracker/loggings.py
fast_tracker/admin/__init__.py
fast_tracker/admin/__main__.py
fast_tracker/admin/run_program.py
fast_tracker/admin/run_python.py
fast_tracker/agent/__init__.py
fast_tracker/agent/protocol/__init__.py
fast_tracker/agent/protocol/udp.py
fast_tracker/bootstrap/__init__.py
fast_tracker/bootstrap/sitecustomize.py
fast_tracker/client/__init__.py
fast_tracker/client/udp.py
fast_tracker/plugins/__init__.py
fast_tracker/plugins/fast_django.py
fast_tracker/plugins/fast_elasticsearch.py
fast_tracker/plugins/fast_falcon.py
fast_tracker/plugins/fast_flask.py
fast_tracker/plugins/fast_http_server.py
fast_tracker/plugins/fast_kafka.py
fast_tracker/plugins/fast_log.py
fast_tracker/plugins/fast_mysqldb.py
fast_tracker/plugins/fast_pymongo.py
fast_tracker/plugins/fast_pymysql.py
fast_tracker/plugins/fast_rabbitmq.py
fast_tracker/plugins/fast_redis.py
fast_tracker/plugins/fast_requests.py
fast_tracker/plugins/fast_rq.py
fast_tracker/plugins/fast_tornado.py
fast_tracker/plugins/fast_urllib3.py
fast_tracker/plugins/fast_urllib_request.py
fast_tracker/report/__init__.py
fast_tracker/report/report_struct.py
fast_tracker/trace/__init__.py
fast_tracker/trace/carrier.py
fast_tracker/trace/context.py
fast_tracker/trace/segment.py
fast_tracker/trace/snapshot.py
fast_tracker/trace/span.py
fast_tracker/trace/tags.py
fast_tracker/trace/ipc/__init__.py
fast_tracker/trace/ipc/process.py
fast_tracker/utils/__init__.py
fast_tracker/utils/counter.py
fast_tracker/utils/exceptions.py
fast_tracker/utils/functions.py
fast_tracker/utils/lang.py
fast_tracker/utils/reader_type.py
fast_tracker-0.2.93.data/scripts/fast-boot
fast_tracker-0.2.93.dist-info/METADATA
fast_tracker-0.2.93.dist-info/WHEEL
fast_tracker-0.2.93.dist-info/entry_points.txt
fast_tracker-0.2.93.dist-info/top_level.txt
fast_tracker-0.2.93.dist-info/RECORD
